localpdb/PDB.py
localpdb/PDBDownloader.py
localpdb/PDBVersioneer.py
localpdb/__init__.py
localpdb/localpdb_setup.py
localpdb/plugins/Biounit.py
localpdb/plugins/DSSP.py
localpdb/plugins/ECOD.py
localpdb/plugins/MasterChain.py
localpdb/plugins/PDBChain.py
localpdb/plugins/PDBClustering.py
localpdb/plugins/PDBSeqresMapper.py
localpdb/plugins/Plugin.py
localpdb/plugins/PluginVersioneer.py
localpdb/plugins/PrepPDBSeqresMapper.py
localpdb/plugins/SIFTS.py
localpdb/plugins/Socket.py
localpdb/plugins/__init__.py
localpdb/plugins/config/Biounit.yml
localpdb/plugins/config/DSSP.yml
localpdb/plugins/config/ECOD.yml
localpdb/plugins/config/MasterChain.yml
localpdb/plugins/config/PDBChain.yml
localpdb/plugins/config/PDBClustering.yml
localpdb/plugins/config/PDBSeqresMapper.yml
localpdb/plugins/config/SIFTS.yml
localpdb/plugins/config/Socket.yml
localpdb/plugins/config/__init__.py
localpdb/plugins/utils/MakeMultimer.py
localpdb/plugins/utils/__init__.py
localpdb/utils/__init__.py
localpdb/utils/config.py
localpdb/utils/errors.py
localpdb/utils/network.py
localpdb/utils/os.py
localpdb/utils/prot.py
localpdb/utils/remote_sources.yml
localpdb/utils/rest_api.py
localpdb/utils/search_api/__init__.py
localpdb/utils/search_api/commands.py
localpdb/utils/search_api/parsers.py
localpdb/utils/search_api/queries.py
localpdb/utils/search_api/search.py
localpdb/utils/search_api/services.py
localpdb/utils/search_api/tools/__init__.py
localpdb/utils/search_api/tools/text_api_input_fetcher.py
localpdb-0.2.9.dist-info/entry_points.txt
localpdb-0.2.9.dist-info/LICENSE
localpdb-0.2.9.dist-info/WHEEL
localpdb-0.2.9.dist-info/METADATA
localpdb-0.2.9.dist-info/RECORD
