Metadata-Version: 2.1
Name: localpdb
Version: 0.2.9
Summary: 
License: MIT
Author: Jan Ludwiczak
Author-email: j.ludwiczak@cent.uw.edu.pl
Requires-Python: >=3.8,<4.0.0
Classifier: License :: OSI Approved :: MIT License
Classifier: Programming Language :: Python :: 3
Classifier: Programming Language :: Python :: 3.8
Classifier: Programming Language :: Python :: 3.9
Requires-Dist: Jinja2 (>=3.0.1,<4.0.0)
Requires-Dist: beautifulsoup4 (>=4.9.3,<5.0.0)
Requires-Dist: biopython (==1.78)
Requires-Dist: coloredlogs (>=15.0,<16.0)
Requires-Dist: ipython_genutils (==0.2.0)
Requires-Dist: pandas (>=2,<3)
Requires-Dist: pyaml (>=20.4.0,<21.0.0)
Requires-Dist: requests (>=2.25.1,<3.0.0)
Requires-Dist: termcolor (>=1.1.0,<2.0.0)
Requires-Dist: tqdm (>=4,<5)
